mux/mux8to1/mux8to1.v
module mux8to1 (
    input a, b, c, d, e, f, g, h,
    input [2:0] sel,
    output reg y
);
    always @(*) begin
        case (sel)
            3'b000: y = a;
            3'b001: y = b;
            3'b010: y = c;
            3'b011: y = d;
            3'b100: y = e;
            3'b101: y = f;
            3'b110: y = g;
            3'b111: y = h;
        endcase
    end
endmodule

mux/mux8to1/tb_mux8to1.v
`timescale 1ns/1ps

module tb_mux8to1;
    reg a, b, c, d, e, f, g, h ;
    reg [2:0]sel;
    wire y;

    mux8to1 uut (.a(a), .b(b), .c(c), .d(d), .e(e), .f(f), .g(g), .h(h), .sel(sel), .y(y));

    integer i;

    initial begin
        $dumpfile("mux8to1.vcd");
        $dumpvars(0, uut);

        // Loop over all 2^11 = 2048 combinations of a, b, c, d, e, f, g, h, [2:0] sel
        for (i = 0; i < 2048; i = i + 1) begin
            {a, b, c, d, e, f, g, h, sel} = i;  // assign inputs
            #10;
        end

        $finish;
    end
endmodule

mux/mux8to1/mux8to1.vcd
$date
	Tue Jun 24 11:45:47 2025
$end
$version
	Icarus Verilog
$end
$timescale
	1ps
$end
$scope module tb_mux8to1 $end
$scope module uut $end
$var wire 1 ! a $end
$var wire 1 " b $end
$var wire 1 # c $end
$var wire 1 $ d $end
$var wire 1 % e $end
$var wire 1 & f $end
$var wire 1 ' g $end
$var wire 1 ( h $end
$var wire 3 ) sel [2:0] $end
$var reg 1 * y $end
$upscope $end
$upscope $end
$enddefinitions $end
$comment Show the parameter values. $end
$dumpall
$end
#0
$dumpvars
0*
b0 )
0(
0'
0&
0%
0$
0#
0"
0!
$end
#10000
b1 )
#20000
b10 )
#30000
b11 )
#40000
b100 )
#50000
b101 )
#60000
b110 )
#70000
b111 )
#80000
1(
b0 )
#90000
b1 )
#100000
b10 )
#110000
b11 )
#120000
b100 )
#130000
b101 )
#140000
b110 )
#150000
1*
b111 )
#160000
0*
1'
0(
b0 )
#170000
b1 )
#180000
b10 )
#190000
b11 )
#200000
b100 )
#210000
b101 )
#220000
1*
b110 )
#230000
0*
b111 )
#240000
1(
b0 )
#250000
b1 )
#260000
b10 )
#270000
b11 )
#280000
b100 )
#290000
b101 )
#300000
1*
b110 )
#310000
b111 )
#320000
0*
1&
0'
0(
b0 )
#330000
b1 )
#340000
b10 )
#350000
b11 )
#360000
b100 )
#370000
1*
b101 )
#380000
0*
b110 )
#390000
b111 )
#400000
1(
b0 )
#410000
b1 )
#420000
b10 )
#430000
b11 )
#440000
b100 )
#450000
1*
b101 )
#460000
0*
b110 )
#470000
1*
b111 )
#480000
0*
1'
0(
b0 )
#490000
b1 )
#500000
b10 )
#510000
b11 )
#520000
b100 )
#530000
1*
b101 )
#540000
b110 )
#550000
0*
b111 )
#560000
1(
b0 )
#570000
b1 )
#580000
b10 )
#590000
b11 )
#600000
b100 )
#610000
1*
b101 )
#620000
b110 )
#630000
b111 )
#640000
0*
1%
0&
0'
0(
b0 )
#650000
b1 )
#660000
b10 )
#670000
b11 )
#680000
1*
b100 )
#690000
0*
b101 )
#700000
b110 )
#710000
b111 )
#720000
1(
b0 )
#730000
b1 )
#740000
b10 )
#750000
b11 )
#760000
1*
b100 )
#770000
0*
b101 )
#780000
b110 )
#790000
1*
b111 )
#800000
0*
1'
0(
b0 )
#810000
b1 )
#820000
b10 )
#830000
b11 )
#840000
1*
b100 )
#850000
0*
b101 )
#860000
1*
b110 )
#870000
0*
b111 )
#880000
1(
b0 )
#890000
b1 )
#900000
b10 )
#910000
b11 )
#920000
1*
b100 )
#930000
0*
b101 )
#940000
1*
b110 )
#950000
b111 )
#960000
0*
1&
0'
0(
b0 )
#970000
b1 )
#980000
b10 )
#990000
b11 )
#1000000
1*
b100 )
#1010000
b101 )
#1020000
0*
b110 )
#1030000
b111 )
#1040000
1(
b0 )
#1050000
b1 )
#1060000
b10 )
#1070000
b11 )
#1080000
1*
b100 )
#1090000
b101 )
#1100000
0*
b110 )
#1110000
1*
b111 )
#1120000
0*
1'
0(
b0 )
#1130000
b1 )
#1140000
b10 )
#1150000
b11 )
#1160000
1*
b100 )
#1170000
b101 )
#1180000
b110 )
#1190000
0*
b111 )
#1200000
1(
b0 )
#1210000
b1 )
#1220000
b10 )
#1230000
b11 )
#1240000
1*
b100 )
#1250000
b101 )
#1260000
b110 )
#1270000
b111 )
#1280000
0*
1$
0%
0&
0'
0(
b0 )
#1290000
b1 )
#1300000
b10 )
#1310000
1*
b11 )
#1320000
0*
b100 )
#1330000
b101 )
#1340000
b110 )
#1350000
b111 )
#1360000
1(
b0 )
#1370000
b1 )
#1380000
b10 )
#1390000
1*
b11 )
#1400000
0*
b100 )
#1410000
b101 )
#1420000
b110 )
#1430000
1*
b111 )
#1440000
0*
1'
0(
b0 )
#1450000
b1 )
#1460000
b10 )
#1470000
1*
b11 )
#1480000
0*
b100 )
#1490000
b101 )
#1500000
1*
b110 )
#1510000
0*
b111 )
#1520000
1(
b0 )
#1530000
b1 )
#1540000
b10 )
#1550000
1*
b11 )
#1560000
0*
b100 )
#1570000
b101 )
#1580000
1*
b110 )
#1590000
b111 )
#1600000
0*
1&
0'
0(
b0 )
#1610000
b1 )
#1620000
b10 )
#1630000
1*
b11 )
#1640000
0*
b100 )
#1650000
1*
b101 )
#1660000
0*
b110 )
#1670000
b111 )
#1680000
1(
b0 )
#1690000
b1 )
#1700000
b10 )
#1710000
1*
b11 )
#1720000
0*
b100 )
#1730000
1*
b101 )
#1740000
0*
b110 )
#1750000
1*
b111 )
#1760000
0*
1'
0(
b0 )
#1770000
b1 )
#1780000
b10 )
#1790000
1*
b11 )
#1800000
0*
b100 )
#1810000
1*
b101 )
#1820000
b110 )
#1830000
0*
b111 )
#1840000
1(
b0 )
#1850000
b1 )
#1860000
b10 )
#1870000
1*
b11 )
#1880000
0*
b100 )
#1890000
1*
b101 )
#1900000
b110 )
#1910000
b111 )
#1920000
0*
1%
0&
0'
0(
b0 )
#1930000
b1 )
#1940000
b10 )
#1950000
1*
b11 )
#1960000
b100 )
#1970000
0*
b101 )
#1980000
b110 )
#1990000
b111 )
#2000000
1(
b0 )
#2010000
b1 )
#2020000
b10 )
#2030000
1*
b11 )
#2040000
b100 )
#2050000
0*
b101 )
#2060000
b110 )
#2070000
1*
b111 )
#2080000
0*
1'
0(
b0 )
#2090000
b1 )
#2100000
b10 )
#2110000
1*
b11 )
#2120000
b100 )
#2130000
0*
b101 )
#2140000
1*
b110 )
#2150000
0*
b111 )
#2160000
1(
b0 )
#2170000
b1 )
#2180000
b10 )
#2190000
1*
b11 )
#2200000
b100 )
#2210000
0*
b101 )
#2220000
1*
b110 )
#2230000
b111 )
#2240000
0*
1&
0'
0(
b0 )
#2250000
b1 )
#2260000
b10 )
#2270000
1*
b11 )
#2280000
b100 )
#2290000
b101 )
#2300000
0*
b110 )
#2310000
b111 )
#2320000
1(
b0 )
#2330000
b1 )
#2340000
b10 )
#2350000
1*
b11 )
#2360000
b100 )
#2370000
b101 )
#2380000
0*
b110 )
#2390000
1*
b111 )
#2400000
0*
1'
0(
b0 )
#2410000
b1 )
#2420000
b10 )
#2430000
1*
b11 )
#2440000
b100 )
#2450000
b101 )
#2460000
b110 )
#2470000
0*
b111 )
#2480000
1(
b0 )
#2490000
b1 )
#2500000
b10 )
#2510000
1*
b11 )
#2520000
b100 )
#2530000
b101 )
#2540000
b110 )
#2550000
b111 )
#2560000
0*
1#
0$
0%
0&
0'
0(
b0 )
#2570000
b1 )
#2580000
1*
b10 )
#2590000
0*
b11 )
#2600000
b100 )
#2610000
b101 )
#2620000
b110 )
#2630000
b111 )
#2640000
1(
b0 )
#2650000
b1 )
#2660000
1*
b10 )
#2670000
0*
b11 )
#2680000
b100 )
#2690000
b101 )
#2700000
b110 )
#2710000
1*
b111 )
#2720000
0*
1'
0(
b0 )
#2730000
b1 )
#2740000
1*
b10 )
#2750000
0*
b11 )
#2760000
b100 )
#2770000
b101 )
#2780000
1*
b110 )
#2790000
0*
b111 )
#2800000
1(
b0 )
#2810000
b1 )
#2820000
1*
b10 )
#2830000
0*
b11 )
#2840000
b100 )
#2850000
b101 )
#2860000
1*
b110 )
#2870000
b111 )
#2880000
0*
1&
0'
0(
b0 )
#2890000
b1 )
#2900000
1*
b10 )
#2910000
0*
b11 )
#2920000
b100 )
#2930000
1*
b101 )
#2940000
0*
b110 )
#2950000
b111 )
#2960000
1(
b0 )
#2970000
b1 )
#2980000
1*
b10 )
#2990000
0*
b11 )
#3000000
b100 )
#3010000
1*
b101 )
#3020000
0*
b110 )
#3030000
1*
b111 )
#3040000
0*
1'
0(
b0 )
#3050000
b1 )
#3060000
1*
b10 )
#3070000
0*
b11 )
#3080000
b100 )
#3090000
1*
b101 )
#3100000
b110 )
#3110000
0*
b111 )
#3120000
1(
b0 )
#3130000
b1 )
#3140000
1*
b10 )
#3150000
0*
b11 )
#3160000
b100 )
#3170000
1*
b101 )
#3180000
b110 )
#3190000
b111 )
#3200000
0*
1%
0&
0'
0(
b0 )
#3210000
b1 )
#3220000
1*
b10 )
#3230000
0*
b11 )
#3240000
1*
b100 )
#3250000
0*
b101 )
#3260000
b110 )
#3270000
b111 )
#3280000
1(
b0 )
#3290000
b1 )
#3300000
1*
b10 )
#3310000
0*
b11 )
#3320000
1*
b100 )
#3330000
0*
b101 )
#3340000
b110 )
#3350000
1*
b111 )
#3360000
0*
1'
0(
b0 )
#3370000
b1 )
#3380000
1*
b10 )
#3390000
0*
b11 )
#3400000
1*
b100 )
#3410000
0*
b101 )
#3420000
1*
b110 )
#3430000
0*
b111 )
#3440000
1(
b0 )
#3450000
b1 )
#3460000
1*
b10 )
#3470000
0*
b11 )
#3480000
1*
b100 )
#3490000
0*
b101 )
#3500000
1*
b110 )
#3510000
b111 )
#3520000
0*
1&
0'
0(
b0 )
#3530000
b1 )
#3540000
1*
b10 )
#3550000
0*
b11 )
#3560000
1*
b100 )
#3570000
b101 )
#3580000
0*
b110 )
#3590000
b111 )
#3600000
1(
b0 )
#3610000
b1 )
#3620000
1*
b10 )
#3630000
0*
b11 )
#3640000
1*
b100 )
#3650000
b101 )
#3660000
0*
b110 )
#3670000
1*
b111 )
#3680000
0*
1'
0(
b0 )
#3690000
b1 )
#3700000
1*
b10 )
#3710000
0*
b11 )
#3720000
1*
b100 )
#3730000
b101 )
#3740000
b110 )
#3750000
0*
b111 )
#3760000
1(
b0 )
#3770000
b1 )
#3780000
1*
b10 )
#3790000
0*
b11 )
#3800000
1*
b100 )
#3810000
b101 )
#3820000
b110 )
#3830000
b111 )
#3840000
0*
1$
0%
0&
0'
0(
b0 )
#3850000
b1 )
#3860000
1*
b10 )
#3870000
b11 )
#3880000
0*
b100 )
#3890000
b101 )
#3900000
b110 )
#3910000
b111 )
#3920000
1(
b0 )
#3930000
b1 )
#3940000
1*
b10 )
#3950000
b11 )
#3960000
0*
b100 )
#3970000
b101 )
#3980000
b110 )
#3990000
1*
b111 )
#4000000
0*
1'
0(
b0 )
#4010000
b1 )
#4020000
1*
b10 )
#4030000
b11 )
#4040000
0*
b100 )
#4050000
b101 )
#4060000
1*
b110 )
#4070000
0*
b111 )
#4080000
1(
b0 )
#4090000
b1 )
#4100000
1*
b10 )
#4110000
b11 )
#4120000
0*
b100 )
#4130000
b101 )
#4140000
1*
b110 )
#4150000
b111 )
#4160000
0*
1&
0'
0(
b0 )
#4170000
b1 )
#4180000
1*
b10 )
#4190000
b11 )
#4200000
0*
b100 )
#4210000
1*
b101 )
#4220000
0*
b110 )
#4230000
b111 )
#4240000
1(
b0 )
#4250000
b1 )
#4260000
1*
b10 )
#4270000
b11 )
#4280000
0*
b100 )
#4290000
1*
b101 )
#4300000
0*
b110 )
#4310000
1*
b111 )
#4320000
0*
1'
0(
b0 )
#4330000
b1 )
#4340000
1*
b10 )
#4350000
b11 )
#4360000
0*
b100 )
#4370000
1*
b101 )
#4380000
b110 )
#4390000
0*
b111 )
#4400000
1(
b0 )
#4410000
b1 )
#4420000
1*
b10 )
#4430000
b11 )
#4440000
0*
b100 )
#4450000
1*
b101 )
#4460000
b110 )
#4470000
b111 )
#4480000
0*
1%
0&
0'
0(
b0 )
#4490000
b1 )
#4500000
1*
b10 )
#4510000
b11 )
#4520000
b100 )
#4530000
0*
b101 )
#4540000
b110 )
#4550000
b111 )
#4560000
1(
b0 )
#4570000
b1 )
#4580000
1*
b10 )
#4590000
b11 )
#4600000
b100 )
#4610000
0*
b101 )
#4620000
b110 )
#4630000
1*
b111 )
#4640000
0*
1'
0(
b0 )
#4650000
b1 )
#4660000
1*
b10 )
#4670000
b11 )
#4680000
b100 )
#4690000
0*
b101 )
#4700000
1*
b110 )
#4710000
0*
b111 )
#4720000
1(
b0 )
#4730000
b1 )
#4740000
1*
b10 )
#4750000
b11 )
#4760000
b100 )
#4770000
0*
b101 )
#4780000
1*
b110 )
#4790000
b111 )
#4800000
0*
1&
0'
0(
b0 )
#4810000
b1 )
#4820000
1*
b10 )
#4830000
b11 )
#4840000
b100 )
#4850000
b101 )
#4860000
0*
b110 )
#4870000
b111 )
#4880000
1(
b0 )
#4890000
b1 )
#4900000
1*
b10 )
#4910000
b11 )
#4920000
b100 )
#4930000
b101 )
#4940000
0*
b110 )
#4950000
1*
b111 )
#4960000
0*
1'
0(
b0 )
#4970000
b1 )
#4980000
1*
b10 )
#4990000
b11 )
#5000000
b100 )
#5010000
b101 )
#5020000
b110 )
#5030000
0*
b111 )
#5040000
1(
b0 )
#5050000
b1 )
#5060000
1*
b10 )
#5070000
b11 )
#5080000
b100 )
#5090000
b101 )
#5100000
b110 )
#5110000
b111 )
#5120000
0*
1"
0#
0$
0%
0&
0'
0(
b0 )
#5130000
1*
b1 )
#5140000
0*
b10 )
#5150000
b11 )
#5160000
b100 )
#5170000
b101 )
#5180000
b110 )
#5190000
b111 )
#5200000
1(
b0 )
#5210000
1*
b1 )
#5220000
0*
b10 )
#5230000
b11 )
#5240000
b100 )
#5250000
b101 )
#5260000
b110 )
#5270000
1*
b111 )
#5280000
0*
1'
0(
b0 )
#5290000
1*
b1 )
#5300000
0*
b10 )
#5310000
b11 )
#5320000
b100 )
#5330000
b101 )
#5340000
1*
b110 )
#5350000
0*
b111 )
#5360000
1(
b0 )
#5370000
1*
b1 )
#5380000
0*
b10 )
#5390000
b11 )
#5400000
b100 )
#5410000
b101 )
#5420000
1*
b110 )
#5430000
b111 )
#5440000
0*
1&
0'
0(
b0 )
#5450000
1*
b1 )
#5460000
0*
b10 )
#5470000
b11 )
#5480000
b100 )
#5490000
1*
b101 )
#5500000
0*
b110 )
#5510000
b111 )
#5520000
1(
b0 )
#5530000
1*
b1 )
#5540000
0*
b10 )
#5550000
b11 )
#5560000
b100 )
#5570000
1*
b101 )
#5580000
0*
b110 )
#5590000
1*
b111 )
#5600000
0*
1'
0(
b0 )
#5610000
1*
b1 )
#5620000
0*
b10 )
#5630000
b11 )
#5640000
b100 )
#5650000
1*
b101 )
#5660000
b110 )
#5670000
0*
b111 )
#5680000
1(
b0 )
#5690000
1*
b1 )
#5700000
0*
b10 )
#5710000
b11 )
#5720000
b100 )
#5730000
1*
b101 )
#5740000
b110 )
#5750000
b111 )
#5760000
0*
1%
0&
0'
0(
b0 )
#5770000
1*
b1 )
#5780000
0*
b10 )
#5790000
b11 )
#5800000
1*
b100 )
#5810000
0*
b101 )
#5820000
b110 )
#5830000
b111 )
#5840000
1(
b0 )
#5850000
1*
b1 )
#5860000
0*
b10 )
#5870000
b11 )
#5880000
1*
b100 )
#5890000
0*
b101 )
#5900000
b110 )
#5910000
1*
b111 )
#5920000
0*
1'
0(
b0 )
#5930000
1*
b1 )
#5940000
0*
b10 )
#5950000
b11 )
#5960000
1*
b100 )
#5970000
0*
b101 )
#5980000
1*
b110 )
#5990000
0*
b111 )
#6000000
1(
b0 )
#6010000
1*
b1 )
#6020000
0*
b10 )
#6030000
b11 )
#6040000
1*
b100 )
#6050000
0*
b101 )
#6060000
1*
b110 )
#6070000
b111 )
#6080000
0*
1&
0'
0(
b0 )
#6090000
1*
b1 )
#6100000
0*
b10 )
#6110000
b11 )
#6120000
1*
b100 )
#6130000
b101 )
#6140000
0*
b110 )
#6150000
b111 )
#6160000
1(
b0 )
#6170000
1*
b1 )
#6180000
0*
b10 )
#6190000
b11 )
#6200000
1*
b100 )
#6210000
b101 )
#6220000
0*
b110 )
#6230000
1*
b111 )
#6240000
0*
1'
0(
b0 )
#6250000
1*
b1 )
#6260000
0*
b10 )
#6270000
b11 )
#6280000
1*
b100 )
#6290000
b101 )
#6300000
b110 )
#6310000
0*
b111 )
#6320000
1(
b0 )
#6330000
1*
b1 )
#6340000
0*
b10 )
#6350000
b11 )
#6360000
1*
b100 )
#6370000
b101 )
#6380000
b110 )
#6390000
b111 )
#6400000
0*
1$
0%
0&
0'
0(
b0 )
#6410000
1*
b1 )
#6420000
0*
b10 )
#6430000
1*
b11 )
#6440000
0*
b100 )
#6450000
b101 )
#6460000
b110 )
#6470000
b111 )
#6480000
1(
b0 )
#6490000
1*
b1 )
#6500000
0*
b10 )
#6510000
1*
b11 )
#6520000
0*
b100 )
#6530000
b101 )
#6540000
b110 )
#6550000
1*
b111 )
#6560000
0*
1'
0(
b0 )
#6570000
1*
b1 )
#6580000
0*
b10 )
#6590000
1*
b11 )
#6600000
0*
b100 )
#6610000
b101 )
#6620000
1*
b110 )
#6630000
0*
b111 )
#6640000
1(
b0 )
#6650000
1*
b1 )
#6660000
0*
b10 )
#6670000
1*
b11 )
#6680000
0*
b100 )
#6690000
b101 )
#6700000
1*
b110 )
#6710000
b111 )
#6720000
0*
1&
0'
0(
b0 )
#6730000
1*
b1 )
#6740000
0*
b10 )
#6750000
1*
b11 )
#6760000
0*
b100 )
#6770000
1*
b101 )
#6780000
0*
b110 )
#6790000
b111 )
#6800000
1(
b0 )
#6810000
1*
b1 )
#6820000
0*
b10 )
#6830000
1*
b11 )
#6840000
0*
b100 )
#6850000
1*
b101 )
#6860000
0*
b110 )
#6870000
1*
b111 )
#6880000
0*
1'
0(
b0 )
#6890000
1*
b1 )
#6900000
0*
b10 )
#6910000
1*
b11 )
#6920000
0*
b100 )
#6930000
1*
b101 )
#6940000
b110 )
#6950000
0*
b111 )
#6960000
1(
b0 )
#6970000
1*
b1 )
#6980000
0*
b10 )
#6990000
1*
b11 )
#7000000
0*
b100 )
#7010000
1*
b101 )
#7020000
b110 )
#7030000
b111 )
#7040000
0*
1%
0&
0'
0(
b0 )
#7050000
1*
b1 )
#7060000
0*
b10 )
#7070000
1*
b11 )
#7080000
b100 )
#7090000
0*
b101 )
#7100000
b110 )
#7110000
b111 )
#7120000
1(
b0 )
#7130000
1*
b1 )
#7140000
0*
b10 )
#7150000
1*
b11 )
#7160000
b100 )
#7170000
0*
b101 )
#7180000
b110 )
#7190000
1*
b111 )
#7200000
0*
1'
0(
b0 )
#7210000
1*
b1 )
#7220000
0*
b10 )
#7230000
1*
b11 )
#7240000
b100 )
#7250000
0*
b101 )
#7260000
1*
b110 )
#7270000
0*
b111 )
#7280000
1(
b0 )
#7290000
1*
b1 )
#7300000
0*
b10 )
#7310000
1*
b11 )
#7320000
b100 )
#7330000
0*
b101 )
#7340000
1*
b110 )
#7350000
b111 )
#7360000
0*
1&
0'
0(
b0 )
#7370000
1*
b1 )
#7380000
0*
b10 )
#7390000
1*
b11 )
#7400000
b100 )
#7410000
b101 )
#7420000
0*
b110 )
#7430000
b111 )
#7440000
1(
b0 )
#7450000
1*
b1 )
#7460000
0*
b10 )
#7470000
1*
b11 )
#7480000
b100 )
#7490000
b101 )
#7500000
0*
b110 )
#7510000
1*
b111 )
#7520000
0*
1'
0(
b0 )
#7530000
1*
b1 )
#7540000
0*
b10 )
#7550000
1*
b11 )
#7560000
b100 )
#7570000
b101 )
#7580000
b110 )
#7590000
0*
b111 )
#7600000
1(
b0 )
#7610000
1*
b1 )
#7620000
0*
b10 )
#7630000
1*
b11 )
#7640000
b100 )
#7650000
b101 )
#7660000
b110 )
#7670000
b111 )
#7680000
0*
1#
0$
0%
0&
0'
0(
b0 )
#7690000
1*
b1 )
#7700000
b10 )
#7710000
0*
b11 )
#7720000
b100 )
#7730000
b101 )
#7740000
b110 )
#7750000
b111 )
#7760000
1(
b0 )
#7770000
1*
b1 )
#7780000
b10 )
#7790000
0*
b11 )
#7800000
b100 )
#7810000
b101 )
#7820000
b110 )
#7830000
1*
b111 )
#7840000
0*
1'
0(
b0 )
#7850000
1*
b1 )
#7860000
b10 )
#7870000
0*
b11 )
#7880000
b100 )
#7890000
b101 )
#7900000
1*
b110 )
#7910000
0*
b111 )
#7920000
1(
b0 )
#7930000
1*
b1 )
#7940000
b10 )
#7950000
0*
b11 )
#7960000
b100 )
#7970000
b101 )
#7980000
1*
b110 )
#7990000
b111 )
#8000000
0*
1&
0'
0(
b0 )
#8010000
1*
b1 )
#8020000
b10 )
#8030000
0*
b11 )
#8040000
b100 )
#8050000
1*
b101 )
#8060000
0*
b110 )
#8070000
b111 )
#8080000
1(
b0 )
#8090000
1*
b1 )
#8100000
b10 )
#8110000
0*
b11 )
#8120000
b100 )
#8130000
1*
b101 )
#8140000
0*
b110 )
#8150000
1*
b111 )
#8160000
0*
1'
0(
b0 )
#8170000
1*
b1 )
#8180000
b10 )
#8190000
0*
b11 )
#8200000
b100 )
#8210000
1*
b101 )
#8220000
b110 )
#8230000
0*
b111 )
#8240000
1(
b0 )
#8250000
1*
b1 )
#8260000
b10 )
#8270000
0*
b11 )
#8280000
b100 )
#8290000
1*
b101 )
#8300000
b110 )
#8310000
b111 )
#8320000
0*
1%
0&
0'
0(
b0 )
#8330000
1*
b1 )
#8340000
b10 )
#8350000
0*
b11 )
#8360000
1*
b100 )
#8370000
0*
b101 )
#8380000
b110 )
#8390000
b111 )
#8400000
1(
b0 )
#8410000
1*
b1 )
#8420000
b10 )
#8430000
0*
b11 )
#8440000
1*
b100 )
#8450000
0*
b101 )
#8460000
b110 )
#8470000
1*
b111 )
#8480000
0*
1'
0(
b0 )
#8490000
1*
b1 )
#8500000
b10 )
#8510000
0*
b11 )
#8520000
1*
b100 )
#8530000
0*
b101 )
#8540000
1*
b110 )
#8550000
0*
b111 )
#8560000
1(
b0 )
#8570000
1*
b1 )
#8580000
b10 )
#8590000
0*
b11 )
#8600000
1*
b100 )
#8610000
0*
b101 )
#8620000
1*
b110 )
#8630000
b111 )
#8640000
0*
1&
0'
0(
b0 )
#8650000
1*
b1 )
#8660000
b10 )
#8670000
0*
b11 )
#8680000
1*
b100 )
#8690000
b101 )
#8700000
0*
b110 )
#8710000
b111 )
#8720000
1(
b0 )
#8730000
1*
b1 )
#8740000
b10 )
#8750000
0*
b11 )
#8760000
1*
b100 )
#8770000
b101 )
#8780000
0*
b110 )
#8790000
1*
b111 )
#8800000
0*
1'
0(
b0 )
#8810000
1*
b1 )
#8820000
b10 )
#8830000
0*
b11 )
#8840000
1*
b100 )
#8850000
b101 )
#8860000
b110 )
#8870000
0*
b111 )
#8880000
1(
b0 )
#8890000
1*
b1 )
#8900000
b10 )
#8910000
0*
b11 )
#8920000
1*
b100 )
#8930000
b101 )
#8940000
b110 )
#8950000
b111 )
#8960000
0*
1$
0%
0&
0'
0(
b0 )
#8970000
1*
b1 )
#8980000
b10 )
#8990000
b11 )
#9000000
0*
b100 )
#9010000
b101 )
#9020000
b110 )
#9030000
b111 )
#9040000
1(
b0 )
#9050000
1*
b1 )
#9060000
b10 )
#9070000
b11 )
#9080000
0*
b100 )
#9090000
b101 )
#9100000
b110 )
#9110000
1*
b111 )
#9120000
0*
1'
0(
b0 )
#9130000
1*
b1 )
#9140000
b10 )
#9150000
b11 )
#9160000
0*
b100 )
#9170000
b101 )
#9180000
1*
b110 )
#9190000
0*
b111 )
#9200000
1(
b0 )
#9210000
1*
b1 )
#9220000
b10 )
#9230000
b11 )
#9240000
0*
b100 )
#9250000
b101 )
#9260000
1*
b110 )
#9270000
b111 )
#9280000
0*
1&
0'
0(
b0 )
#9290000
1*
b1 )
#9300000
b10 )
#9310000
b11 )
#9320000
0*
b100 )
#9330000
1*
b101 )
#9340000
0*
b110 )
#9350000
b111 )
#9360000
1(
b0 )
#9370000
1*
b1 )
#9380000
b10 )
#9390000
b11 )
#9400000
0*
b100 )
#9410000
1*
b101 )
#9420000
0*
b110 )
#9430000
1*
b111 )
#9440000
0*
1'
0(
b0 )
#9450000
1*
b1 )
#9460000
b10 )
#9470000
b11 )
#9480000
0*
b100 )
#9490000
1*
b101 )
#9500000
b110 )
#9510000
0*
b111 )
#9520000
1(
b0 )
#9530000
1*
b1 )
#9540000
b10 )
#9550000
b11 )
#9560000
0*
b100 )
#9570000
1*
b101 )
#9580000
b110 )
#9590000
b111 )
#9600000
0*
1%
0&
0'
0(
b0 )
#9610000
1*
b1 )
#9620000
b10 )
#9630000
b11 )
#9640000
b100 )
#9650000
0*
b101 )
#9660000
b110 )
#9670000
b111 )
#9680000
1(
b0 )
#9690000
1*
b1 )
#9700000
b10 )
#9710000
b11 )
#9720000
b100 )
#9730000
0*
b101 )
#9740000
b110 )
#9750000
1*
b111 )
#9760000
0*
1'
0(
b0 )
#9770000
1*
b1 )
#9780000
b10 )
#9790000
b11 )
#9800000
b100 )
#9810000
0*
b101 )
#9820000
1*
b110 )
#9830000
0*
b111 )
#9840000
1(
b0 )
#9850000
1*
b1 )
#9860000
b10 )
#9870000
b11 )
#9880000
b100 )
#9890000
0*
b101 )
#9900000
1*
b110 )
#9910000
b111 )
#9920000
0*
1&
0'
0(
b0 )
#9930000
1*
b1 )
#9940000
b10 )
#9950000
b11 )
#9960000
b100 )
#9970000
b101 )
#9980000
0*
b110 )
#9990000
b111 )
#10000000
1(
b0 )
#10010000
1*
b1 )
#10020000
b10 )
#10030000
b11 )
#10040000
b100 )
#10050000
b101 )
#10060000
0*
b110 )
#10070000
1*
b111 )
#10080000
0*
1'
0(
b0 )
#10090000
1*
b1 )
#10100000
b10 )
#10110000
b11 )
#10120000
b100 )
#10130000
b101 )
#10140000
b110 )
#10150000
0*
b111 )
#10160000
1(
b0 )
#10170000
1*
b1 )
#10180000
b10 )
#10190000
b11 )
#10200000
b100 )
#10210000
b101 )
#10220000
b110 )
#10230000
b111 )
#10240000
1!
0"
0#
0$
0%
0&
0'
0(
b0 )
#10250000
0*
b1 )
#10260000
b10 )
#10270000
b11 )
#10280000
b100 )
#10290000
b101 )
#10300000
b110 )
#10310000
b111 )
#10320000
1*
1(
b0 )
#10330000
0*
b1 )
#10340000
b10 )
#10350000
b11 )
#10360000
b100 )
#10370000
b101 )
#10380000
b110 )
#10390000
1*
b111 )
#10400000
1'
0(
b0 )
#10410000
0*
b1 )
#10420000
b10 )
#10430000
b11 )
#10440000
b100 )
#10450000
b101 )
#10460000
1*
b110 )
#10470000
0*
b111 )
#10480000
1*
1(
b0 )
#10490000
0*
b1 )
#10500000
b10 )
#10510000
b11 )
#10520000
b100 )
#10530000
b101 )
#10540000
1*
b110 )
#10550000
b111 )
#10560000
1&
0'
0(
b0 )
#10570000
0*
b1 )
#10580000
b10 )
#10590000
b11 )
#10600000
b100 )
#10610000
1*
b101 )
#10620000
0*
b110 )
#10630000
b111 )
#10640000
1*
1(
b0 )
#10650000
0*
b1 )
#10660000
b10 )
#10670000
b11 )
#10680000
b100 )
#10690000
1*
b101 )
#10700000
0*
b110 )
#10710000
1*
b111 )
#10720000
1'
0(
b0 )
#10730000
0*
b1 )
#10740000
b10 )
#10750000
b11 )
#10760000
b100 )
#10770000
1*
b101 )
#10780000
b110 )
#10790000
0*
b111 )
#10800000
1*
1(
b0 )
#10810000
0*
b1 )
#10820000
b10 )
#10830000
b11 )
#10840000
b100 )
#10850000
1*
b101 )
#10860000
b110 )
#10870000
b111 )
#10880000
1%
0&
0'
0(
b0 )
#10890000
0*
b1 )
#10900000
b10 )
#10910000
b11 )
#10920000
1*
b100 )
#10930000
0*
b101 )
#10940000
b110 )
#10950000
b111 )
#10960000
1*
1(
b0 )
#10970000
0*
b1 )
#10980000
b10 )
#10990000
b11 )
#11000000
1*
b100 )
#11010000
0*
b101 )
#11020000
b110 )
#11030000
1*
b111 )
#11040000
1'
0(
b0 )
#11050000
0*
b1 )
#11060000
b10 )
#11070000
b11 )
#11080000
1*
b100 )
#11090000
0*
b101 )
#11100000
1*
b110 )
#11110000
0*
b111 )
#11120000
1*
1(
b0 )
#11130000
0*
b1 )
#11140000
b10 )
#11150000
b11 )
#11160000
1*
b100 )
#11170000
0*
b101 )
#11180000
1*
b110 )
#11190000
b111 )
#11200000
1&
0'
0(
b0 )
#11210000
0*
b1 )
#11220000
b10 )
#11230000
b11 )
#11240000
1*
b100 )
#11250000
b101 )
#11260000
0*
b110 )
#11270000
b111 )
#11280000
1*
1(
b0 )
#11290000
0*
b1 )
#11300000
b10 )
#11310000
b11 )
#11320000
1*
b100 )
#11330000
b101 )
#11340000
0*
b110 )
#11350000
1*
b111 )
#11360000
1'
0(
b0 )
#11370000
0*
b1 )
#11380000
b10 )
#11390000
b11 )
#11400000
1*
b100 )
#11410000
b101 )
#11420000
b110 )
#11430000
0*
b111 )
#11440000
1*
1(
b0 )
#11450000
0*
b1 )
#11460000
b10 )
#11470000
b11 )
#11480000
1*
b100 )
#11490000
b101 )
#11500000
b110 )
#11510000
b111 )
#11520000
1$
0%
0&
0'
0(
b0 )
#11530000
0*
b1 )
#11540000
b10 )
#11550000
1*
b11 )
#11560000
0*
b100 )
#11570000
b101 )
#11580000
b110 )
#11590000
b111 )
#11600000
1*
1(
b0 )
#11610000
0*
b1 )
#11620000
b10 )
#11630000
1*
b11 )
#11640000
0*
b100 )
#11650000
b101 )
#11660000
b110 )
#11670000
1*
b111 )
#11680000
1'
0(
b0 )
