decoders_and_encoder/decoder3to8/decoder3to8.v
module decoder3to8 (
    input [2:0] in,  // 2-bit input
    output reg [7:0] out  // 4-bit output
);
    always @(*) begin
        case (in)
            3'b000: out = 8'b00000001;
            3'b001: out = 8'b00000010;
            3'b010: out = 8'b00000100;
            3'b011: out = 8'b00001000;
            3'b100: out = 8'b00010000;
            3'b101: out = 8'b00100000;
            3'b110: out = 8'b01000000;
            3'b111: out = 8'b10000000;
            default: out = 8'b00000000;
        endcase
    end
endmodule

decoders_and_encoder/decoder3to8/tb_decoder3to8.v
`timescale 1ns/1ps
module 
    tb_decoder3to8;
    reg [2:0] in;
    wire [7:0] out;

    decoder3to8 uut(.in(in), .out(out));  // Instantiate the module

    integer i;

    initial begin
        $dumpfile("decoder3to8_case.vcd");
        $dumpvars(0, uut);  
  
        $display("Time\tin\tout");
        for (i = 0; i < 8; i = i + 1) begin
            in = i;
            #10;
            $display("%0t\t%b\t%b", $time, in, out);
        end
        $finish;
    end
endmodule

decoders_and_encoder/decoder3to8/decoder3to8_case.vcd
$date
	Thu Jun 26 11:22:10 2025
$end
$version
	Icarus Verilog
$end
$timescale
	1ps
$end
$scope module tb_decoder3to8 $end
$scope module uut $end
$var wire 3 ! in [2:0] $end
$var reg 8 " out [7:0] $end
$upscope $end
$upscope $end
$enddefinitions $end
$comment Show the parameter values. $end
$dumpall
$end
#0
$dumpvars
b1 "
b0 !
$end
#10000
b10 "
b1 !
#20000
b100 "
b10 !
#30000
b1000 "
b11 !
#40000
b10000 "
b100 !
#50000
b100000 "
b101 !
#60000
b1000000 "
b110 !
#70000
b10000000 "
b111 !
