codes/mux/mux4to1/mux4to1.v
module mux4to1 (
    input a,     
    input b,
    input c,
    input d,     
    input [1:0] sel,   
    output y     // output
);
    assign y = (sel == 2'b00) ? a :
               (sel == 2'b01) ? b :
               (sel == 2'b10) ? c :
               d;
endmodule

codes/mux/mux4to1/tb_mux4to1.v
`timescale 1ns/1ps

module tb_mux4to1;
    reg a, b, c, d;
    reg [1:0]sel;
    wire y;

    mux4to1 uut (.a(a), .b(b), .c(c), .d(d), .sel(sel), .y(y));

    integer i;

    initial begin
        $dumpfile("mux4to1.vcd");
        $dumpvars(0, uut);

        // Loop over all 2^6 = 64 combinations of a, b, [1:0] sel
        for (i = 0; i < 64; i = i + 1) begin
            {a, b, c, d, sel} = i;  // assign inputs
            #20;
        end

        $finish;
    end
endmodule

codes/mux/mux4to1/mux4to1.vcd
$date
	Tue Jun 24 11:27:10 2025
$end
$version
	Icarus Verilog
$end
$timescale
	1ps
$end
$scope module tb_mux4to1 $end
$scope module uut $end
$var wire 1 ! a $end
$var wire 1 " b $end
$var wire 1 # c $end
$var wire 1 $ d $end
$var wire 2 % sel [1:0] $end
$var wire 1 & y $end
$upscope $end
$upscope $end
$enddefinitions $end
$comment Show the parameter values. $end
$dumpall
$end
#0
$dumpvars
0&
b0 %
0$
0#
0"
0!
$end
#20000
b1 %
#40000
b10 %
#60000
b11 %
#80000
1$
b0 %
#100000
b1 %
#120000
b10 %
#140000
1&
b11 %
#160000
0&
1#
0$
b0 %
#180000
b1 %
#200000
1&
b10 %
#220000
0&
b11 %
#240000
1$
b0 %
#260000
b1 %
#280000
1&
b10 %
#300000
b11 %
#320000
0&
1"
0#
0$
b0 %
#340000
1&
b1 %
#360000
0&
b10 %
#380000
b11 %
#400000
1$
b0 %
#420000
1&
b1 %
#440000
0&
b10 %
#460000
1&
b11 %
#480000
0&
1#
0$
b0 %
#500000
1&
b1 %
#520000
b10 %
#540000
0&
b11 %
#560000
1$
b0 %
#580000
1&
b1 %
#600000
b10 %
#620000
b11 %
#640000
1!
0"
0#
0$
b0 %
#660000
0&
b1 %
#680000
b10 %
#700000
b11 %
#720000
1&
1$
b0 %
#740000
0&
b1 %
#760000
b10 %
#780000
1&
b11 %
#800000
1#
0$
b0 %
#820000
0&
b1 %
#840000
1&
b10 %
#860000
0&
b11 %
#880000
1&
1$
b0 %
#900000
0&
b1 %
#920000
1&
b10 %
#940000
b11 %
#960000
1"
0#
0$
b0 %
#980000
b1 %
#1000000
0&
b10 %
#1020000
b11 %
#1040000
1&
1$
b0 %
#1060000
b1 %
#1080000
0&
b10 %
#1100000
1&
b11 %
#1120000
1#
0$
b0 %
#1140000
b1 %
#1160000
b10 %
#1180000
0&
b11 %
#1200000
1&
1$
b0 %
#1220000
b1 %
#1240000
b10 %
#1260000
b11 %
