And/and_gate.v
module 
	and_gate(input a, input b, output y);
    	assign y = a & b;
endmodule

And/tb_and.v
`timescale 1ns/1ps
module 
    tb_and;
    reg a, b;
    wire y;

    and_gate uut(.a(a), .b(b), .y(y));  // Instantiate the module

    initial begin
        $dumpfile("wave.vcd");
        $dumpvars(0, tb_and);

        a = 0; b = 0; #10;
        a = 0; b = 1; #10;
        a = 1; b = 0; #10;
        a = 1; b = 1; #10;
	a = 0; b = 0; #10;
        a = 0; b = 1; #10;
        a = 1; b = 0; #10;
        a = 1; b = 1; #10;
	a = 0; b = 0; #10;
        a = 0; b = 0; #10;
        a = 1; b = 1; #10;
        a = 1; b = 1; #10;
        $finish;
    end
endmodule

And/wave.vcd
$date
	Sun Jun 22 13:05:24 2025
$end
$version
	Icarus Verilog
$end
$timescale
	1ps
$end
$scope module tb_and $end
$var wire 1 ! y $end
$var reg 1 " a $end
$var reg 1 # b $end
$scope module uut $end
$var wire 1 " a $end
$var wire 1 # b $end
$var wire 1 ! y $end
$upscope $end
$upscope $end
$enddefinitions $end
$comment Show the parameter values. $end
$dumpall
$end
#0
$dumpvars
0#
0"
0!
$end
#10000
1#
#20000
0#
1"
#30000
1!
1#
#40000
0!
0#
0"
#50000
1#
#60000
0#
1"
#70000
1!
1#
#80000
0!
0#
0"
#100000
1!
1#
1"
