decoders_and_encoder/4to2 priority encoder/priority_encoder_4to2.v
module priority_encoder_4to2 (
    input [3:0] D,          // Inputs D3 (MSB) to D0 (LSB)
    output reg [1:0] Y,     // Encoded output
    output reg V            // Valid signal
);
    always @(*) begin
        casez (D)  // 'z' allows don't care
            4'b1???: begin Y = 2'b11; V = 1; end
            4'b01??: begin Y = 2'b10; V = 1; end
            4'b001?: begin Y = 2'b01; V = 1; end
            4'b0001: begin Y = 2'b00; V = 1; end
            default: begin Y = 2'b00; V = 0; end
        endcase
    end
endmodule

decoders_and_encoder/4to2 priority encoder/tb_priority_encoder_4to2.v
`timescale 1ns/1ps

module tb_priority_encoder_4to2;

    reg [3:0] D;
    wire [1:0] Y;
    wire V;

    priority_encoder_4to2 uut (.D(D), .Y(Y), .V(V));

    integer i;

    initial begin
        $dumpfile("priority_encoder_4to2.vcd");
        $dumpvars(0, uut);

        $display("Time\tD\tY\tV");

        for (i = 0; i < 16; i = i + 1) begin
            D = i;
            #10;
            $display("%0t\t%b\t%b\t%b", $time, D, Y, V);
        end

        $finish;
    end

endmodule

decoders_and_encoder/4to2 priority encoder/priority_encoder_4to2.vcd
$date
	Thu Jun 26 19:25:48 2025
$end
$version
	Icarus Verilog
$end
$timescale
	1ps
$end
$scope module tb_priority_encoder_4to2 $end
$scope module uut $end
$var wire 4 ! D [3:0] $end
$var reg 1 " V $end
$var reg 2 # Y [1:0] $end
$upscope $end
$upscope $end
$enddefinitions $end
$comment Show the parameter values. $end
$dumpall
$end
#0
$dumpvars
b0 #
0"
b0 !
$end
#10000
1"
b1 !
#20000
b1 #
b10 !
#30000
b11 !
#40000
b10 #
b100 !
#50000
b101 !
#60000
b110 !
#70000
b111 !
#80000
b11 #
b1000 !
#90000
b1001 !
#100000
b1010 !
#110000
b1011 !
#120000
b1100 !
#130000
b1101 !
#140000
b1110 !
#150000
b1111 !
