codes/3_input_Xor_followed_by_AND/Xor_and_gate.v
module 
	Xor_and_gate(input a, input b, input c,  output y);
    	assign y = (a^b) & c;
endmodule

codes/3_input_Xor_followed_by_AND/tb_xor_and.v
`timescale 1ns/1ps
module 
    tb_xor_and;
    reg a, b, c;
    wire y;

    Xor_and_gate uut(.a(a), .b(b), .c(c), .y(y));  // Instantiate the module

    initial begin
        $dumpfile("wave_xor_and.vcd");
        $dumpvars(0, tb_xor_and);

        a=0; b=0; c=0; #10
	a=0; b=0; c=1; #10
	a=0; b=1; c=0; #10
	a=0; b=1; c=1; #10
	a=1; b=0; c=0; #10
	a=1; b=0; c=1; #10
	a=1; b=1; c=0; #10
	a=1; b=1; c=1; #10
        $finish;
    end
endmodule

codes/3_input_Xor_followed_by_AND/wave_xor_and.vcd
$date
	Mon Jun 23 11:24:38 2025
$end
$version
	Icarus Verilog
$end
$timescale
	1ps
$end
$scope module tb_xor_and $end
$var wire 1 ! y $end
$var reg 1 " a $end
$var reg 1 # b $end
$var reg 1 $ c $end
$scope module uut $end
$var wire 1 " a $end
$var wire 1 # b $end
$var wire 1 $ c $end
$var wire 1 ! y $end
$upscope $end
$upscope $end
$enddefinitions $end
$comment Show the parameter values. $end
$dumpall
$end
#0
$dumpvars
0$
0#
0"
0!
$end
#10000
1$
#20000
0$
1#
#30000
1!
1$
#40000
0!
0$
0#
1"
#50000
1!
1$
#60000
0!
0$
1#
#70000
1$
