codes/decoders_and_encoder/decoder3to8/decoder3to8_gate.v
module decoder3to8_gate (
    input a, b, c,        // a = MSB, c = LSB
    output [7:0] out
);
    assign out[7] = ~a & ~b & ~c;
    assign out[6] = ~a & ~b &  c;
    assign out[5] = ~a &  b & ~c;
    assign out[4] = ~a &  b &  c;
    assign out[3] =  a & ~b & ~c;
    assign out[2] =  a & ~b &  c;
    assign out[1] =  a &  b & ~c;
    assign out[0] =  a &  b &  c;
endmodule

codes/decoders_and_encoder/decoder3to8/tb_decoder3to8_gate.v
`timescale 1ns/1ps
module 
    tb_decoder3to8_gate;
    reg a, b, c;
    wire [7:0] out;

    decoder3to8_gate uut(.a(a), .b(b), .c(c), .out(out));  // Instantiate the module

    integer i;

    initial begin
        $dumpfile("decoder3to8_gate.vcd");
        $dumpvars(0, uut);  
  
        $display("Time\t a b c\tout");
        for (i = 0; i < 8; i = i + 1) begin
            {a,b,c} = i;
            #10;
            $display("%0t\t %b %b %b\t %b", $time, a, b, c, out);
        end
        $finish;
    end
endmodule

codes/decoders_and_encoder/decoder3to8/decoder3to8_gate.vcd
$date
	Thu Jun 26 11:21:57 2025
$end
$version
	Icarus Verilog
$end
$timescale
	1ps
$end
$scope module tb_decoder3to8_gate $end
$scope module uut $end
$var wire 1 ! a $end
$var wire 1 " b $end
$var wire 1 # c $end
$var wire 8 $ out [7:0] $end
$upscope $end
$upscope $end
$enddefinitions $end
$comment Show the parameter values. $end
$dumpall
$end
#0
$dumpvars
b10000000 $
0#
0"
0!
$end
#10000
b1000000 $
1#
#20000
b100000 $
1"
0#
#30000
b10000 $
1#
#40000
b1000 $
1!
0"
0#
#50000
b100 $
1#
#60000
b10 $
1"
0#
#70000
b1 $
1#
