mux/mux2to1/mux2to1.v
module mux2to1 (
    input a,     // input 0
    input b,     // input 1
    input sel,   // selector
    output y     // output
);
    assign y = (sel) ? b : a;  // if sel==1, output=b; else output=a
endmodule

mux/mux2to1/tb_mux2to1.v
`timescale 1ns/1ps

module tb_mux2to1;
    reg a, b, sel;
    wire y;

    mux2to1 uut (.a(a), .b(b), .sel(sel), .y(y));

    integer i;

    initial begin
        $dumpfile("mux2to1.vcd");
        $dumpvars(0, uut);

        // Loop over all 2^3 = 8 combinations of a, b, sel
        for (i = 0; i < 8; i = i + 1) begin
            {a, b, sel} = i;  // assign inputs
            #10;
        end

        $finish;
    end
endmodule

mux/mux2to1/mux2to1.vcd
$date
	Tue Jun 24 11:03:15 2025
$end
$version
	Icarus Verilog
$end
$timescale
	1ps
$end
$scope module tb_mux2to1 $end
$scope module uut $end
$var wire 1 ! a $end
$var wire 1 " b $end
$var wire 1 # sel $end
$var wire 1 $ y $end
$upscope $end
$upscope $end
$enddefinitions $end
$comment Show the parameter values. $end
$dumpall
$end
#0
$dumpvars
0$
0#
0"
0!
$end
#10000
1#
#20000
1"
0#
#30000
1$
1#
#40000
1!
0"
0#
#50000
0$
1#
#60000
1$
1"
0#
#70000
1#
